{
  "0": {
    "basicblocks": 1,
    "calls": "6 8 4 5",
    "file": "pfb_top.cpp",
    "fileloc": 3,
    "instructions": 45,
    "name": "pfb_multichannel",
    "total_instructions": 916
  },
  "1": {
    "basicblocks": 3,
    "calls": "",
    "file": "pfb_io.cpp",
    "fileloc": 80,
    "instructions": 72,
    "name": "repack",
    "stores": {
      "L": 8
    },
    "total_instructions": 72
  },
  "2": {
    "basicblocks": 4,
    "calls": "",
    "file": "hls_fft_x_complex.h",
    "fileloc": 509,
    "instructions": 26,
    "name": "fft_syn<config1>",
    "total_instructions": 26
  },
  "3": {
    "basicblocks": 1,
    "calls": "2",
    "file": "hls_fft_x_complex.h",
    "fileloc": 696,
    "instructions": 5,
    "name": "fft<config1>",
    "total_instructions": 31
  },
  "4": {
    "basicblocks": 5,
    "calls": "7 3 3 3 3 1",
    "file": "pfb_fft.cpp",
    "fileloc": 3,
    "instructions": 149,
    "name": "fft",
    "stores": {
      "L": 1
    },
    "total_instructions": 465
  },
  "5": {
    "basicblocks": 3,
    "calls": "",
    "file": "pfb_io.cpp",
    "fileloc": 28,
    "instructions": 33,
    "name": "write_outputs",
    "total_instructions": 33
  },
  "6": {
    "basicblocks": 3,
    "calls": "",
    "file": "pfb_io.cpp",
    "fileloc": 3,
    "instructions": 24,
    "name": "read_inputs",
    "total_instructions": 24
  },
  "7": {
    "basicblocks": 3,
    "calls": "",
    "file": "pfb_io.cpp",
    "fileloc": 60,
    "instructions": 100,
    "loads": {
      "L": 8
    },
    "name": "unpack",
    "stores": {
      "L": 8
    },
    "total_instructions": 120
  },
  "8": {
    "basicblocks": 7,
    "calls": "",
    "file": "pfb_compute.cpp",
    "fileloc": 3,
    "instructions": 349,
    "loads": {
      "G": 30,
      "L": 1
    },
    "name": "decimate_pfb",
    "stores": {
      "G": 11
    },
    "total_instructions": 349
  }
}